django_stubs_patch/__init__.py
django_stubs_patch/patch.py
django_stubs_patch-0.1.0.dist-info/LICENSE
django_stubs_patch-0.1.0.dist-info/WHEEL
django_stubs_patch-0.1.0.dist-info/METADATA
django_stubs_patch-0.1.0.dist-info/RECORD
