Metadata-Version: 2.1
Name: django-stubs-patch
Version: 0.1.0
Summary: A pmypy django-stubs patch work for python3.6
Home-page: https://github.com/mrlyc/django-stubs-patch
Author: MrLYC
Author-email: fimyikong@gmail.com
Requires-Python: >=3.6.1
Classifier: Programming Language :: Python :: 3
Classifier: Programming Language :: Python :: 3.10
Classifier: Programming Language :: Python :: 3.7
Classifier: Programming Language :: Python :: 3.8
Classifier: Programming Language :: Python :: 3.9
Requires-Dist: django (==3.2.12)
Requires-Dist: django-stubs (==1.9.0)
Requires-Dist: mypy (>=0.971,<0.972)
Project-URL: Documentation, https://mrlyc.github.io/django-stubs-patch/
Project-URL: Repository, https://github.com/mrlyc/django-stubs-patch
